SajadEncFree/SajadEncFree.py
SajadEncFree/SajadEncFree_fast.py
SajadEncFree/__init__.py
tests/SajadEncFree_file_test.py
tests/SajadEncFree_test.py
tests/__init__.py
tests/generate_old_pickles.py
tests/test_backward_compat.py
tests/testutils.py
SajadFreeEnc-1.dist-info/LICENSE
SajadFreeEnc-1.dist-info/METADATA
SajadFreeEnc-1.dist-info/WHEEL
SajadFreeEnc-1.dist-info/top_level.txt
SajadFreeEnc-1.dist-info/RECORD
